{  "types":[
  {
    "originalName": "SummaryChangedEventArgs",
    "originalNamespace": "Infragistics.Controls.Grids.Implementation",
    "packageName": "igniteui-data-grids",
    "names":[{"platform": "Blazor","fileName": "SummaryChangedEventArgs.cs","mappedName": "IgbSummaryChangedEventArgs"}],
    "members":[
      {"names":[{"platform": "Blazor", "mappedType": "string",  "mappedName": "ID"}], "originalName": "ID"},
      {"names":[{"platform": "Blazor", "mappedType": "bool",    "mappedName": "IsEnabled"}], "originalName": "IsEnabled"} ]
  }]
}